xstatstests/__init__.py
xstatstests/_version.py
xstatstests/core.py
xstatstests/scipy.py
xstatstests/utils.py
xstatstests/tests/__init__.py
xstatstests/tests/fixtures.py
xstatstests/tests/test_core.py
xstatstests/tests/test_scipy.py
xstatstests-0.0.3.dist-info/LICENSE
xstatstests-0.0.3.dist-info/METADATA
xstatstests-0.0.3.dist-info/WHEEL
xstatstests-0.0.3.dist-info/top_level.txt
xstatstests-0.0.3.dist-info/RECORD
