Metadata-Version: 2.1
Name: xstatstests
Version: 0.0.3
Summary: Statistical tests xarray objects
Home-page: https://github.com/dougiesquire/xstatstests
Author: Dougie Squire
License: UNKNOWN
Platform: UNKNOWN
Classifier: Development Status :: 4 - Beta
Classifier: Programming Language :: Python :: 3
Classifier: License :: OSI Approved :: MIT License
Classifier: Operating System :: OS Independent
Requires-Python: >=3.7
License-File: LICENSE
Requires-Dist: xarray
Requires-Dist: scipy (>=1.8.0)
